{
  "name": "Use of social media in the US by gender (Pew Research Center)",
  "title": "Use of social media in the US by gender (Pew Research Center)",
  "id": 4195,
  "description": "Respondents who did not give an answer are excluded from the estimates.",
  "sources": [
    {
      "name": "Pew Research Center (2019)",
      "link": "https://www.pewresearch.org/fact-tank/2018/12/10/social-media-outpaces-print-newspapers-in-the-u-s-as-a-news-source/",
      "retrievedDate": "29 August 2019",
      "additionalInfo": "Respondents who did not give an answer are excluded from the estimates.",
      "dataPublishedBy": "Pew Research Center",
      "dataPublisherSource": "Survey conducted Jan. 8 - Feb. 7, 2019"
    }
  ],
  "owidTags": [
    "Internet",
    "Social Media"
  ],
  "resources": [
    {
      "path": "Use of social media in the US by gender (Pew Research Center).csv",
      "schema": {
        "fields": [
          {
            "name": "Entity",
            "type": "string"
          },
          {
            "name": "Year",
            "type": "year"
          },
          {
            "name": "Social media use among men in the US (%)",
            "type": "any",
            "description": null,
            "owidDisplaySettings": "{\"unit\": \"%\", \"shortUnit\": \"%\"}"
          },
          {
            "name": "Social media use among women in the US (%)",
            "type": "any",
            "description": null,
            "owidDisplaySettings": "{\"unit\": \"%\", \"shortUnit\": \"%\", \"numDecimalPlaces\": 1}"
          }
        ]
      }
    }
  ]
}