{
  "name": "Water and Sanitation (WHO WASH, 2021)",
  "title": "Water and Sanitation (WHO WASH, 2021)",
  "id": 5332,
  "description": "",
  "sources": [
    {
      "name": "WHO/UNICEF Joint Monitoring Programme (JMP) for Water Supply and Sanitation",
      "link": "https://washdata.org/data",
      "dataPublishedBy": "WHO/UNICEF Joint Monitoring Programme (JMP) for Water Supply and Sanitation"
    }
  ],
  "owidTags": [
    "Water Use",
    "Sanitation"
  ],
  "resources": [
    {
      "path": "Water and Sanitation (WHO WASH, 2021).csv",
      "schema": {
        "fields": [
          {
            "name": "Entity",
            "type": "string"
          },
          {
            "name": "Year",
            "type": "year"
          },
          {
            "name": "wat_imp",
            "type": "any",
            "description": null,
            "owidDisplaySettings": "{}"
          },
          {
            "name": "wat_bas",
            "type": "any",
            "description": null,
            "owidDisplaySettings": "{}"
          },
          {
            "name": "wat_lim",
            "type": "any",
            "description": null,
            "owidDisplaySettings": "{}"
          },
          {
            "name": "wat_unimp",
            "type": "any",
            "description": null,
            "owidDisplaySettings": "{}"
          },
          {
            "name": "wat_sur",
            "type": "any",
            "description": null,
            "owidDisplaySettings": "{}"
          },
          {
            "name": "wat_pip",
            "type": "any",
            "description": null,
            "owidDisplaySettings": "{}"
          },
          {
            "name": "wat_npip",
            "type": "any",
            "description": null,
            "owidDisplaySettings": "{}"
          },
          {
            "name": "wat_premises",
            "type": "any",
            "description": null,
            "owidDisplaySettings": "{}"
          },
          {
            "name": "wat_available",
            "type": "any",
            "description": null,
            "owidDisplaySettings": "{}"
          },
          {
            "name": "wat_quality",
            "type": "any",
            "description": null,
            "owidDisplaySettings": "{}"
          },
          {
            "name": "wat_sm",
            "type": "any",
            "description": null,
            "owidDisplaySettings": "{}"
          },
          {
            "name": "san_imp",
            "type": "any",
            "description": null,
            "owidDisplaySettings": "{}"
          },
          {
            "name": "san_bas",
            "type": "any",
            "description": null,
            "owidDisplaySettings": "{}"
          },
          {
            "name": "san_lim",
            "type": "any",
            "description": null,
            "owidDisplaySettings": "{}"
          },
          {
            "name": "san_unimp",
            "type": "any",
            "description": null,
            "owidDisplaySettings": "{}"
          },
          {
            "name": "san_od",
            "type": "any",
            "description": null,
            "owidDisplaySettings": "{}"
          },
          {
            "name": "san_lat",
            "type": "any",
            "description": null,
            "owidDisplaySettings": "{}"
          },
          {
            "name": "san_sep",
            "type": "any",
            "description": null,
            "owidDisplaySettings": "{}"
          },
          {
            "name": "san_sew",
            "type": "any",
            "description": null,
            "owidDisplaySettings": "{}"
          },
          {
            "name": "san_sdo_sm",
            "type": "any",
            "description": null,
            "owidDisplaySettings": "{}"
          },
          {
            "name": "san_fst_sm",
            "type": "any",
            "description": null,
            "owidDisplaySettings": "{}"
          },
          {
            "name": "san_sew_sm",
            "type": "any",
            "description": null,
            "owidDisplaySettings": "{}"
          },
          {
            "name": "san_sm",
            "type": "any",
            "description": null,
            "owidDisplaySettings": "{}"
          },
          {
            "name": "hyg_bas",
            "type": "any",
            "description": null,
            "owidDisplaySettings": "{}"
          },
          {
            "name": "hyg_lim",
            "type": "any",
            "description": null,
            "owidDisplaySettings": "{}"
          },
          {
            "name": "hyg_nfac",
            "type": "any",
            "description": null,
            "owidDisplaySettings": "{}"
          },
          {
            "name": "wat_imp_number",
            "type": "any",
            "description": null,
            "owidDisplaySettings": "{}"
          },
          {
            "name": "wat_bas_number",
            "type": "any",
            "description": null,
            "owidDisplaySettings": "{}"
          },
          {
            "name": "wat_lim_number",
            "type": "any",
            "description": null,
            "owidDisplaySettings": "{}"
          },
          {
            "name": "wat_unimp_number",
            "type": "any",
            "description": null,
            "owidDisplaySettings": "{}"
          },
          {
            "name": "wat_sur_number",
            "type": "any",
            "description": null,
            "owidDisplaySettings": "{}"
          },
          {
            "name": "wat_pip_number",
            "type": "any",
            "description": null,
            "owidDisplaySettings": "{}"
          },
          {
            "name": "wat_npip_number",
            "type": "any",
            "description": null,
            "owidDisplaySettings": "{}"
          },
          {
            "name": "wat_premises_number",
            "type": "any",
            "description": null,
            "owidDisplaySettings": "{}"
          },
          {
            "name": "wat_available_number",
            "type": "any",
            "description": null,
            "owidDisplaySettings": "{}"
          },
          {
            "name": "wat_quality_number",
            "type": "any",
            "description": null,
            "owidDisplaySettings": "{}"
          },
          {
            "name": "wat_sm_number",
            "type": "any",
            "description": null,
            "owidDisplaySettings": "{}"
          },
          {
            "name": "san_imp_number",
            "type": "any",
            "description": null,
            "owidDisplaySettings": "{}"
          },
          {
            "name": "san_bas_number",
            "type": "any",
            "description": null,
            "owidDisplaySettings": "{}"
          },
          {
            "name": "san_lim_number",
            "type": "any",
            "description": null,
            "owidDisplaySettings": "{}"
          },
          {
            "name": "san_unimp_number",
            "type": "any",
            "description": null,
            "owidDisplaySettings": "{}"
          },
          {
            "name": "san_od_number",
            "type": "any",
            "description": null,
            "owidDisplaySettings": "{}"
          },
          {
            "name": "san_lat_number",
            "type": "any",
            "description": null,
            "owidDisplaySettings": "{}"
          },
          {
            "name": "san_sep_number",
            "type": "any",
            "description": null,
            "owidDisplaySettings": "{}"
          },
          {
            "name": "san_sew_number",
            "type": "any",
            "description": null,
            "owidDisplaySettings": "{}"
          },
          {
            "name": "san_sdo_sm_number",
            "type": "any",
            "description": null,
            "owidDisplaySettings": "{}"
          },
          {
            "name": "san_fst_sm_number",
            "type": "any",
            "description": null,
            "owidDisplaySettings": "{}"
          },
          {
            "name": "san_sm_number",
            "type": "any",
            "description": null,
            "owidDisplaySettings": "{}"
          },
          {
            "name": "san_sew_sm_number",
            "type": "any",
            "description": null,
            "owidDisplaySettings": "{}"
          },
          {
            "name": "hyg_bas_number",
            "type": "any",
            "description": null,
            "owidDisplaySettings": "{}"
          },
          {
            "name": "hyg_lim_number",
            "type": "any",
            "description": null,
            "owidDisplaySettings": "{}"
          },
          {
            "name": "hyg_nfac_number",
            "type": "any",
            "description": null,
            "owidDisplaySettings": "{}"
          },
          {
            "name": "wat_imp_rural",
            "type": "any",
            "description": null,
            "owidDisplaySettings": "{}"
          },
          {
            "name": "wat_bas_rural",
            "type": "any",
            "description": null,
            "owidDisplaySettings": "{}"
          },
          {
            "name": "wat_lim_rural",
            "type": "any",
            "description": null,
            "owidDisplaySettings": "{}"
          },
          {
            "name": "wat_unimp_rural",
            "type": "any",
            "description": null,
            "owidDisplaySettings": "{}"
          },
          {
            "name": "wat_sur_rural",
            "type": "any",
            "description": null,
            "owidDisplaySettings": "{}"
          },
          {
            "name": "wat_pip_rural",
            "type": "any",
            "description": null,
            "owidDisplaySettings": "{}"
          },
          {
            "name": "wat_npip_rural",
            "type": "any",
            "description": null,
            "owidDisplaySettings": "{}"
          },
          {
            "name": "wat_premises_rural",
            "type": "any",
            "description": null,
            "owidDisplaySettings": "{}"
          },
          {
            "name": "wat_available_rural",
            "type": "any",
            "description": null,
            "owidDisplaySettings": "{}"
          },
          {
            "name": "wat_quality_rural",
            "type": "any",
            "description": null,
            "owidDisplaySettings": "{}"
          },
          {
            "name": "wat_sm_rural",
            "type": "any",
            "description": null,
            "owidDisplaySettings": "{}"
          },
          {
            "name": "san_imp_rural",
            "type": "any",
            "description": null,
            "owidDisplaySettings": "{}"
          },
          {
            "name": "san_bas_rural",
            "type": "any",
            "description": null,
            "owidDisplaySettings": "{}"
          },
          {
            "name": "san_lim_rural",
            "type": "any",
            "description": null,
            "owidDisplaySettings": "{}"
          },
          {
            "name": "san_unimp_rural",
            "type": "any",
            "description": null,
            "owidDisplaySettings": "{}"
          },
          {
            "name": "san_od_rural",
            "type": "any",
            "description": null,
            "owidDisplaySettings": "{}"
          },
          {
            "name": "san_lat_rural",
            "type": "any",
            "description": null,
            "owidDisplaySettings": "{}"
          },
          {
            "name": "san_sep_rural",
            "type": "any",
            "description": null,
            "owidDisplaySettings": "{}"
          },
          {
            "name": "san_sew_rural",
            "type": "any",
            "description": null,
            "owidDisplaySettings": "{}"
          },
          {
            "name": "san_sdo_sm_rural",
            "type": "any",
            "description": null,
            "owidDisplaySettings": "{}"
          },
          {
            "name": "san_fst_sm_rural",
            "type": "any",
            "description": null,
            "owidDisplaySettings": "{}"
          },
          {
            "name": "san_sew_sm_rural",
            "type": "any",
            "description": null,
            "owidDisplaySettings": "{}"
          },
          {
            "name": "san_sm_rural",
            "type": "any",
            "description": null,
            "owidDisplaySettings": "{}"
          },
          {
            "name": "hyg_bas_rural",
            "type": "any",
            "description": null,
            "owidDisplaySettings": "{}"
          },
          {
            "name": "hyg_lim_rural",
            "type": "any",
            "description": null,
            "owidDisplaySettings": "{}"
          },
          {
            "name": "hyg_nfac_rural",
            "type": "any",
            "description": null,
            "owidDisplaySettings": "{}"
          },
          {
            "name": "wat_imp_number_rural",
            "type": "any",
            "description": null,
            "owidDisplaySettings": "{}"
          },
          {
            "name": "wat_bas_number_rural",
            "type": "any",
            "description": null,
            "owidDisplaySettings": "{}"
          },
          {
            "name": "wat_lim_number_rural",
            "type": "any",
            "description": null,
            "owidDisplaySettings": "{}"
          },
          {
            "name": "wat_unimp_number_rural",
            "type": "any",
            "description": null,
            "owidDisplaySettings": "{}"
          },
          {
            "name": "wat_sur_number_rural",
            "type": "any",
            "description": null,
            "owidDisplaySettings": "{}"
          },
          {
            "name": "wat_pip_number_rural",
            "type": "any",
            "description": null,
            "owidDisplaySettings": "{}"
          },
          {
            "name": "wat_npip_number_rural",
            "type": "any",
            "description": null,
            "owidDisplaySettings": "{}"
          },
          {
            "name": "wat_premises_number_rural",
            "type": "any",
            "description": null,
            "owidDisplaySettings": "{}"
          },
          {
            "name": "wat_available_number_rural",
            "type": "any",
            "description": null,
            "owidDisplaySettings": "{}"
          },
          {
            "name": "wat_quality_number_rural",
            "type": "any",
            "description": null,
            "owidDisplaySettings": "{}"
          },
          {
            "name": "wat_sm_number_rural",
            "type": "any",
            "description": null,
            "owidDisplaySettings": "{}"
          },
          {
            "name": "san_imp_number_rural",
            "type": "any",
            "description": null,
            "owidDisplaySettings": "{}"
          },
          {
            "name": "san_bas_number_rural",
            "type": "any",
            "description": null,
            "owidDisplaySettings": "{}"
          },
          {
            "name": "san_lim_number_rural",
            "type": "any",
            "description": null,
            "owidDisplaySettings": "{}"
          },
          {
            "name": "san_unimp_number_rural",
            "type": "any",
            "description": null,
            "owidDisplaySettings": "{}"
          },
          {
            "name": "san_od_number_rural",
            "type": "any",
            "description": null,
            "owidDisplaySettings": "{}"
          },
          {
            "name": "san_lat_number_rural",
            "type": "any",
            "description": null,
            "owidDisplaySettings": "{}"
          },
          {
            "name": "san_sep_number_rural",
            "type": "any",
            "description": null,
            "owidDisplaySettings": "{}"
          },
          {
            "name": "san_sew_number_rural",
            "type": "any",
            "description": null,
            "owidDisplaySettings": "{}"
          },
          {
            "name": "san_sdo_sm_number_rural",
            "type": "any",
            "description": null,
            "owidDisplaySettings": "{}"
          },
          {
            "name": "san_fst_sm_number_rural",
            "type": "any",
            "description": null,
            "owidDisplaySettings": "{}"
          },
          {
            "name": "san_sm_number_rural",
            "type": "any",
            "description": null,
            "owidDisplaySettings": "{}"
          },
          {
            "name": "san_sew_sm_number_rural",
            "type": "any",
            "description": null,
            "owidDisplaySettings": "{}"
          },
          {
            "name": "hyg_bas_number_rural",
            "type": "any",
            "description": null,
            "owidDisplaySettings": "{}"
          },
          {
            "name": "hyg_lim_number_rural",
            "type": "any",
            "description": null,
            "owidDisplaySettings": "{}"
          },
          {
            "name": "hyg_nfac_number_rural",
            "type": "any",
            "description": null,
            "owidDisplaySettings": "{}"
          },
          {
            "name": "wat_lim_urban",
            "type": "any",
            "description": null,
            "owidDisplaySettings": "{}"
          },
          {
            "name": "wat_imp_urban",
            "type": "any",
            "description": null,
            "owidDisplaySettings": "{}"
          },
          {
            "name": "wat_bas_urban",
            "type": "any",
            "description": null,
            "owidDisplaySettings": "{}"
          },
          {
            "name": "wat_unimp_urban",
            "type": "any",
            "description": null,
            "owidDisplaySettings": "{}"
          },
          {
            "name": "wat_sur_urban",
            "type": "any",
            "description": null,
            "owidDisplaySettings": "{}"
          },
          {
            "name": "wat_pip_urban",
            "type": "any",
            "description": null,
            "owidDisplaySettings": "{}"
          },
          {
            "name": "wat_npip_urban",
            "type": "any",
            "description": null,
            "owidDisplaySettings": "{}"
          },
          {
            "name": "wat_premises_urban",
            "type": "any",
            "description": null,
            "owidDisplaySettings": "{}"
          },
          {
            "name": "wat_available_urban",
            "type": "any",
            "description": null,
            "owidDisplaySettings": "{}"
          },
          {
            "name": "wat_quality_urban",
            "type": "any",
            "description": null,
            "owidDisplaySettings": "{}"
          },
          {
            "name": "wat_sm_urban",
            "type": "any",
            "description": null,
            "owidDisplaySettings": "{}"
          },
          {
            "name": "san_imp_sew",
            "type": "any",
            "description": null,
            "owidDisplaySettings": "{}"
          },
          {
            "name": "san_imp_sep",
            "type": "any",
            "description": null,
            "owidDisplaySettings": "{}"
          },
          {
            "name": "san_imp_lat",
            "type": "any",
            "description": null,
            "owidDisplaySettings": "{}"
          },
          {
            "name": "san_bas_sew",
            "type": "any",
            "description": null,
            "owidDisplaySettings": "{}"
          },
          {
            "name": "san_bas_sep",
            "type": "any",
            "description": null,
            "owidDisplaySettings": "{}"
          },
          {
            "name": "san_bas_lat",
            "type": "any",
            "description": null,
            "owidDisplaySettings": "{}"
          },
          {
            "name": "san_onsite_sm",
            "type": "any",
            "description": null,
            "owidDisplaySettings": "{}"
          },
          {
            "name": "san_imp_sew_rural",
            "type": "any",
            "description": null,
            "owidDisplaySettings": "{}"
          },
          {
            "name": "san_imp_sep_rural",
            "type": "any",
            "description": null,
            "owidDisplaySettings": "{}"
          },
          {
            "name": "san_imp_lat_rural",
            "type": "any",
            "description": null,
            "owidDisplaySettings": "{}"
          },
          {
            "name": "san_bas_sew_rural",
            "type": "any",
            "description": null,
            "owidDisplaySettings": "{}"
          },
          {
            "name": "san_bas_sep_rural",
            "type": "any",
            "description": null,
            "owidDisplaySettings": "{}"
          },
          {
            "name": "san_bas_lat_rural",
            "type": "any",
            "description": null,
            "owidDisplaySettings": "{}"
          },
          {
            "name": "san_onsite_sm_rural",
            "type": "any",
            "description": null,
            "owidDisplaySettings": "{}"
          },
          {
            "name": "san_imp_urban",
            "type": "any",
            "description": null,
            "owidDisplaySettings": "{}"
          },
          {
            "name": "san_bas_urban",
            "type": "any",
            "description": null,
            "owidDisplaySettings": "{}"
          },
          {
            "name": "san_lim_urban",
            "type": "any",
            "description": null,
            "owidDisplaySettings": "{}"
          },
          {
            "name": "san_unimp_urban",
            "type": "any",
            "description": null,
            "owidDisplaySettings": "{}"
          },
          {
            "name": "san_od_urban",
            "type": "any",
            "description": null,
            "owidDisplaySettings": "{}"
          },
          {
            "name": "san_imp_sew_urban",
            "type": "any",
            "description": null,
            "owidDisplaySettings": "{}"
          },
          {
            "name": "san_imp_sep_urban",
            "type": "any",
            "description": null,
            "owidDisplaySettings": "{}"
          },
          {
            "name": "san_imp_lat_urban",
            "type": "any",
            "description": null,
            "owidDisplaySettings": "{}"
          },
          {
            "name": "san_bas_sew_urban",
            "type": "any",
            "description": null,
            "owidDisplaySettings": "{}"
          },
          {
            "name": "san_bas_sep_urban",
            "type": "any",
            "description": null,
            "owidDisplaySettings": "{}"
          },
          {
            "name": "san_bas_lat_urban",
            "type": "any",
            "description": null,
            "owidDisplaySettings": "{}"
          },
          {
            "name": "san_sdo_sm_urban",
            "type": "any",
            "description": null,
            "owidDisplaySettings": "{}"
          },
          {
            "name": "san_fst_sm_urban",
            "type": "any",
            "description": null,
            "owidDisplaySettings": "{}"
          },
          {
            "name": "san_sew_sm_urban",
            "type": "any",
            "description": null,
            "owidDisplaySettings": "{}"
          },
          {
            "name": "san_sm_urban",
            "type": "any",
            "description": null,
            "owidDisplaySettings": "{}"
          },
          {
            "name": "san_onsite_sm_urban",
            "type": "any",
            "description": null,
            "owidDisplaySettings": "{}"
          },
          {
            "name": "hyg_bas_urban",
            "type": "any",
            "description": null,
            "owidDisplaySettings": "{}"
          },
          {
            "name": "hyg_lim_urban",
            "type": "any",
            "description": null,
            "owidDisplaySettings": "{}"
          },
          {
            "name": "hyg_nfac_urban",
            "type": "any",
            "description": null,
            "owidDisplaySettings": "{}"
          },
          {
            "name": "san_lat_urban",
            "type": "any",
            "description": null,
            "owidDisplaySettings": "{}"
          },
          {
            "name": "san_sep_urban",
            "type": "any",
            "description": null,
            "owidDisplaySettings": "{}"
          },
          {
            "name": "san_sew_urban",
            "type": "any",
            "description": null,
            "owidDisplaySettings": "{}"
          },
          {
            "name": "wat_imp_number_urban",
            "type": "any",
            "description": null,
            "owidDisplaySettings": "{}"
          },
          {
            "name": "wat_bas_number_urban",
            "type": "any",
            "description": null,
            "owidDisplaySettings": "{}"
          },
          {
            "name": "wat_lim_number_urban",
            "type": "any",
            "description": null,
            "owidDisplaySettings": "{}"
          },
          {
            "name": "wat_unimp_number_urban",
            "type": "any",
            "description": null,
            "owidDisplaySettings": "{}"
          },
          {
            "name": "wat_sur_number_urban",
            "type": "any",
            "description": null,
            "owidDisplaySettings": "{}"
          },
          {
            "name": "wat_pip_number_urban",
            "type": "any",
            "description": null,
            "owidDisplaySettings": "{}"
          },
          {
            "name": "wat_npip_number_urban",
            "type": "any",
            "description": null,
            "owidDisplaySettings": "{}"
          },
          {
            "name": "wat_premises_number_urban",
            "type": "any",
            "description": null,
            "owidDisplaySettings": "{}"
          },
          {
            "name": "wat_available_number_urban",
            "type": "any",
            "description": null,
            "owidDisplaySettings": "{}"
          },
          {
            "name": "wat_quality_number_urban",
            "type": "any",
            "description": null,
            "owidDisplaySettings": "{}"
          },
          {
            "name": "wat_sm_number_urban",
            "type": "any",
            "description": null,
            "owidDisplaySettings": "{}"
          },
          {
            "name": "san_imp_number_urban",
            "type": "any",
            "description": null,
            "owidDisplaySettings": "{}"
          },
          {
            "name": "san_bas_number_urban",
            "type": "any",
            "description": null,
            "owidDisplaySettings": "{}"
          },
          {
            "name": "san_lim_number_urban",
            "type": "any",
            "description": null,
            "owidDisplaySettings": "{}"
          },
          {
            "name": "san_unimp_number_urban",
            "type": "any",
            "description": null,
            "owidDisplaySettings": "{}"
          },
          {
            "name": "san_od_number_urban",
            "type": "any",
            "description": null,
            "owidDisplaySettings": "{}"
          },
          {
            "name": "san_lat_number_urban",
            "type": "any",
            "description": null,
            "owidDisplaySettings": "{}"
          },
          {
            "name": "san_sep_number_urban",
            "type": "any",
            "description": null,
            "owidDisplaySettings": "{}"
          },
          {
            "name": "san_sew_number_urban",
            "type": "any",
            "description": null,
            "owidDisplaySettings": "{}"
          },
          {
            "name": "san_sdo_sm_number_urban",
            "type": "any",
            "description": null,
            "owidDisplaySettings": "{}"
          },
          {
            "name": "san_fst_sm_number_urban",
            "type": "any",
            "description": null,
            "owidDisplaySettings": "{}"
          },
          {
            "name": "san_sm_number_urban",
            "type": "any",
            "description": null,
            "owidDisplaySettings": "{}"
          },
          {
            "name": "san_sew_sm_number_urban",
            "type": "any",
            "description": null,
            "owidDisplaySettings": "{}"
          },
          {
            "name": "hyg_bas_number_urban",
            "type": "any",
            "description": null,
            "owidDisplaySettings": "{}"
          },
          {
            "name": "hyg_lim_number_urban",
            "type": "any",
            "description": null,
            "owidDisplaySettings": "{}"
          },
          {
            "name": "hyg_nfac_number_urban",
            "type": "any",
            "description": null,
            "owidDisplaySettings": "{}"
          },
          {
            "name": "wat_bas_minus_sm",
            "type": "any",
            "description": null,
            "owidDisplaySettings": "{}"
          },
          {
            "name": "wat_bas_minus_sm_number",
            "type": "any",
            "description": null,
            "owidDisplaySettings": "{}"
          },
          {
            "name": "san_bas_minus_sm",
            "type": "any",
            "description": null,
            "owidDisplaySettings": "{}"
          },
          {
            "name": "san_bas_minus_sm_number",
            "type": "any",
            "description": null,
            "owidDisplaySettings": "{}"
          },
          {
            "name": "wat_bas_minus_sm_rural",
            "type": "any",
            "description": null,
            "owidDisplaySettings": "{}"
          },
          {
            "name": "wat_bas_minus_sm_number_rural",
            "type": "any",
            "description": null,
            "owidDisplaySettings": "{}"
          },
          {
            "name": "san_bas_minus_sm_rural",
            "type": "any",
            "description": null,
            "owidDisplaySettings": "{}"
          },
          {
            "name": "san_bas_minus_sm_number_rural",
            "type": "any",
            "description": null,
            "owidDisplaySettings": "{}"
          },
          {
            "name": "wat_bas_minus_sm_urban",
            "type": "any",
            "description": null,
            "owidDisplaySettings": "{}"
          },
          {
            "name": "wat_bas_minus_sm_number_urban",
            "type": "any",
            "description": null,
            "owidDisplaySettings": "{}"
          },
          {
            "name": "san_bas_minus_sm_urban",
            "type": "any",
            "description": null,
            "owidDisplaySettings": "{}"
          },
          {
            "name": "san_bas_minus_sm_number_urban",
            "type": "any",
            "description": null,
            "owidDisplaySettings": "{}"
          }
        ]
      }
    }
  ]
}