{
  "name": "Microprocessor clock speed- Ray Kurzweil",
  "title": "Microprocessor clock speed- Ray Kurzweil",
  "id": 1853,
  "description": "Microprocessor clock speed measures the number of pulses per second generated by an oscillator that sets the tempo for the processor. It is measured in hertz (pulses per second).\n\nRay Kurzweil's original sources were as follows:\n\nData from 1976–1999: E. R. Berndt, E. R. Dulberger, and N. J. Rappaport, “Price and Quality of Desktop and Mobile Personal Computers: A Quarter Century of History,” July 17, 2000, http://www.nber.org/~confer/2000/si2000/berndt.pdf.\n\nData from 2001–2016: ITRS, 2002 Update, On-Chip Local Clock in Table 4c: Performance and Package Chips: Frequency On-Chip Wiring Levels—Near-Term Years, p.167.",
  "sources": [
    {
      "name": "Microprocessor clock speed- Ray Kurzweil",
      "dataPublishedBy": "Ray Kurzweil (2005). The Singularity Is Near: When Humans Transcend Biology.",
      "dataPublisherSource": null,
      "link": "http://www.singularity.com/charts/page61.html",
      "retrievedDate": "2017-11-30",
      "additionalInfo": "Microprocessor clock speed measures the number of pulses per second generated by an oscillator that sets the tempo for the processor. It is measured in hertz (pulses per second).\n\nRay Kurzweil's original sources were as follows:\n\nData from 1976–1999: E. R. Berndt, E. R. Dulberger, and N. J. Rappaport, “Price and Quality of Desktop and Mobile Personal Computers: A Quarter Century of History,” July 17, 2000, http://www.nber.org/~confer/2000/si2000/berndt.pdf.\n\nData from 2001–2016: ITRS, 2002 Update, On-Chip Local Clock in Table 4c: Performance and Package Chips: Frequency On-Chip Wiring Levels—Near-Term Years, p.167."
    }
  ],
  "owidTags": [
    "Technological Progress"
  ],
  "resources": [
    {
      "path": "Microprocessor clock speed- Ray Kurzweil.csv",
      "schema": {
        "fields": [
          {
            "name": "Entity",
            "type": "string"
          },
          {
            "name": "Year",
            "type": "year"
          },
          {
            "name": "Microprocessor clock speed",
            "type": "any",
            "description": "",
            "owidDisplaySettings": {
              "shortUnit": "Hz"
            }
          }
        ]
      }
    }
  ]
}