{
  "name": "Heights of early Europeans - Hermanussen (2003)",
  "title": "Heights of early Europeans - Hermanussen (2003)",
  "id": 672,
  "description": "This series combines figures from two published datasets.\n\nData on human heights in Early Europeans in the Eastern Mediterranean region was sourced from Hermanussen (2013). Stature of Early Europeans. These heights are provided for specific historical periods: where values are provided over a time range (for example, 10000-8000 BC), we have have allocated a date in the middle of this range (9000 BC, in this example).\n\nTo compare how historical heights have evolved into the 19th and 20th century, we have combined this series with data for Italy in the period 1810-1980 from the University of Tuebingen. Available at: http://www.uni-tuebingen.de/fakultaeten/wirtschafts-und-sozialwissenschaftliche-fakultaet/faecher/wirtschaftswissenschaft/lehrstuehle/volkswirtschaftslehre/wirtschaftsgeschichte/data-hub-height.html\n\nReferences:\n\nHermanussen, M. (2003). Stature of early Europeans. HORMONES-ATHENS-, 2, 175-178. Available at: http://www.hormones.gr/pdf/Stature_europeans.pdf",
  "sources": [
    {
      "name": "Heights of early Europeans - Hermanussen (2003)",
      "dataPublishedBy": null,
      "dataPublisherSource": null,
      "link": null,
      "retrievedDate": null,
      "additionalInfo": "This series combines figures from two published datasets.\n\nData on human heights in Early Europeans in the Eastern Mediterranean region was sourced from Hermanussen (2013). Stature of Early Europeans. These heights are provided for specific historical periods: where values are provided over a time range (for example, 10000-8000 BC), we have have allocated a date in the middle of this range (9000 BC, in this example).\n\nTo compare how historical heights have evolved into the 19th and 20th century, we have combined this series with data for Italy in the period 1810-1980 from the University of Tuebingen. Available at: http://www.uni-tuebingen.de/fakultaeten/wirtschafts-und-sozialwissenschaftliche-fakultaet/faecher/wirtschaftswissenschaft/lehrstuehle/volkswirtschaftslehre/wirtschaftsgeschichte/data-hub-height.html\n\nReferences:\n\nHermanussen, M. (2003). Stature of early Europeans. HORMONES-ATHENS-, 2, 175-178. Available at: http://www.hormones.gr/pdf/Stature_europeans.pdf"
    }
  ],
  "owidTags": [
    "Human Height"
  ],
  "resources": [
    {
      "path": "Heights of early Europeans - Hermanussen (2003).csv",
      "schema": {
        "fields": [
          {
            "name": "Entity",
            "type": "string"
          },
          {
            "name": "Year",
            "type": "year"
          },
          {
            "name": "Males (Hermanussen (2003))",
            "type": "any",
            "description": "Height of males measured in centimetres. ",
            "owidDisplaySettings": {}
          },
          {
            "name": "Females (Hermanussen (2003))",
            "type": "any",
            "description": "Height of females measured in centimetres.",
            "owidDisplaySettings": {}
          }
        ]
      }
    }
  ]
}